cluster/__init__.py
cluster/categorical_cluster.py
cluster/clustering_loop.py
cluster/clustering_utils.py
cluster/prepare_data.py
categorical_cluster-0.3.dist-info/METADATA
categorical_cluster-0.3.dist-info/WHEEL
categorical_cluster-0.3.dist-info/top_level.txt
categorical_cluster-0.3.dist-info/RECORD
