Metadata-Version: 2.1
Name: categorical-cluster
Version: 0.3
Summary: A package for clustering categorical data
Home-page: https://github.com/bajor/categorical-cluster
Author: Maciej Bajor
Author-email: maciekbajor@gmail.com
Classifier: Development Status :: 3 - Alpha
Classifier: Intended Audience :: Developers
Classifier: License :: OSI Approved :: MIT License
Classifier: Programming Language :: Python :: 3
